adnator/__init__.py
adnator/coalescent_simulation.py
adnator/io.py
adnator/makefile
adnator/read_simulation.cpp
adnator/read_simulation.py
adnator/simulation.py
adnator-1.3.5.dist-info/licenses/LICENSE
adnator-1.3.5.dist-info/METADATA
adnator-1.3.5.dist-info/WHEEL
adnator-1.3.5.dist-info/top_level.txt
adnator-1.3.5.dist-info/RECORD
