Metadata-Version: 2.4
Name: adnator
Version: 1.3.5
Summary: A realistic-ish aDNA simulator
Home-page: https://github.com/Jazpy/adnator
Author: Jazeps Medina Tretmanis
Author-email: jaz.medtre@gmail.com
Classifier: Programming Language :: Python :: 3
Classifier: License :: OSI Approved :: MIT License
Classifier: Operating System :: POSIX :: Linux
License-File: LICENSE
Requires-Dist: attrs>=23.2.0
Requires-Dist: demes>=0.2.3
Requires-Dist: msprime>=1.3.1
Requires-Dist: newick>=1.9.0
Requires-Dist: numpy>=1.26.4
Requires-Dist: PyYAML>=6.0.1
Requires-Dist: referencing>=0.35.1
Requires-Dist: rpds-py>=0.18.1
Requires-Dist: ruamel.yaml>=0.18.6
Requires-Dist: ruamel.yaml.clib>=0.2.8
Requires-Dist: svgwrite>=1.4.3
Requires-Dist: tskit>=0.5.6
Dynamic: author
Dynamic: author-email
Dynamic: classifier
Dynamic: home-page
Dynamic: license-file
Dynamic: requires-dist
Dynamic: summary
